README.md
setup.py
pybase100/__init__.py
pybase100.egg-info/PKG-INFO
pybase100.egg-info/SOURCES.txt
pybase100.egg-info/dependency_links.txt
pybase100.egg-info/not-zip-safe
pybase100.egg-info/top_level.txt