Metadata-Version: 2.1
Name: pybase100
Version: 0.3a0
Summary: A Python version of Base100 encoding mechanism
Home-page: https://github.com/MasterGroosha/pybase100
Author: Evgeny Petrov
Author-email: groosha@protonmail.com
License: The Unlicence
Platform: UNKNOWN
